README.md
setup.cfg
setup.py
pyez/__init__.py
pyez/apptypes.py
pyez/client_conn.py
pyez/gen.py
pyez/msg.py
pyez/worker_conn.py
pyez.egg-info/PKG-INFO
pyez.egg-info/SOURCES.txt
pyez.egg-info/dependency_links.txt
pyez.egg-info/top_level.txt