Metadata-Version: 1.2
Name: pyez
Version: 0.1.1
Summary: Worker API for the EZ Arch framework
Home-page: https://github.com/tengelisconsulting/pyez
Author: Liam Tengelis
Author-email: liam@tengelisconsulting.com
License: UNKNOWN
Download-URL: https://github.com/tengelisconsulting/pyez/archive/v0.1.1.tar.gz
Platform: UNKNOWN
Requires-Python: >=3.8
